adase_api/__init__.py
adase_api/geo.py
adase_api/helpers.py
adase_api/metrics.py
adase_api/sentiment.py
adase_api/docs/__init__.py
adase_api/docs/config.py
adase_api/schemas/__init__.py
adase_api/schemas/geo.py
adase_api/schemas/sentiment.py
adase_api/visualise/geo.py
adase_api/visualise/map.py
adase_api/visualise/regime.py
adase_api/visualise/signals.py
adase_api-0.5.7.dist-info/licenses/LICENSE.txt
adase_api-0.5.7.dist-info/METADATA
adase_api-0.5.7.dist-info/WHEEL
adase_api-0.5.7.dist-info/top_level.txt
adase_api-0.5.7.dist-info/RECORD
