Metadata-Version: 2.4
Name: adase-api
Version: 0.5.7
Summary: Sentiment Explorer Python API
Home-page: https://github.com/meely-ai/adase-api
Author: Alpha Data Analytics PSA
Author-email: tech@adalytica.io
Project-URL: Bug Tracker, https://github.com/meely-ai/adase-api/issues
Classifier: Programming Language :: Python :: 3
Classifier: Operating System :: OS Independent
License-File: LICENSE.txt
Requires-Dist: numpy>=1.18.5
Requires-Dist: pandas>=1.1.5
Requires-Dist: requests>=2.23.0
Requires-Dist: asgiref>=3.5.2
Requires-Dist: aiohttp>=3.7
Requires-Dist: setuptools-git>=1.2
Requires-Dist: scipy>=1.7.1
Requires-Dist: aiohttp-retry>=2.8.3
Requires-Dist: loguru==0.7.3
Requires-Dist: pydantic<=1.10.21,>=1.9.0
Dynamic: license-file
